[
    {
        "FullName":  "C:\\GeoHistory\\backend\\.env",
        "Name":  ".env",
        "Extension":  ".env",
        "Length":  350,
        "LastWriteTimeUtc":  "\/Date(1756672542000)\/"
    },
    {
        "FullName":  "C:\\GeoHistory\\backend\\index.js",
        "Name":  "index.js",
        "Extension":  ".js",
        "Length":  14821,
        "LastWriteTimeUtc":  "\/Date(1756674148000)\/"
    },
    {
        "FullName":  "C:\\GeoHistory\\backend\\package-lock.json",
        "Name":  "package-lock.json",
        "Extension":  ".json",
        "Length":  42198,
        "LastWriteTimeUtc":  "\/Date(1756672604000)\/"
    },
    {
        "FullName":  "C:\\GeoHistory\\backend\\package.json",
        "Name":  "package.json",
        "Extension":  ".json",
        "Length":  371,
        "LastWriteTimeUtc":  "\/Date(1756672576000)\/"
    }
]
